rewrite_pdf/__gs.py
rewrite_pdf/__init__.py
rewrite_pdf/bin/__init__.py
rewrite_pdf/bin/rewrite_pdf.py
rewrite_pdf-0.1.dist-info/METADATA
rewrite_pdf-0.1.dist-info/WHEEL
rewrite_pdf-0.1.dist-info/entry_points.txt
rewrite_pdf-0.1.dist-info/top_level.txt
rewrite_pdf-0.1.dist-info/RECORD
