Metadata-Version: 2.1
Name: rewrite-pdf
Version: 0.1
Summary: A wrapper around ghostscript to rewrite pdf
Home-page: UNKNOWN
Author: Jean-Benoist Leger
Author-email: jb@leger.tf
License: BSD-2
Keywords: pdf ghostscript
Platform: UNKNOWN
Classifier: Development Status :: 3 - Alpha
Classifier: License :: OSI Approved
Classifier: Programming Language :: Python :: 3 :: Only
Requires-Python: >=3
Provides-Extra: test
